Workbook

Sheet Resumo
A1: PLANILHA CONTROLE DE OBRA PREMIUM | B1: PLANILHA CONTROLE DE OBRA PREMIUM | C1: PLANILHA CONTROLE DE OBRA PREMIUM | D1: PLANILHA CONTROLE DE OBRA PREMIUM | E1: PLANILHA CONTROLE DE OBRA PREMIUM | F1: PLANILHA CONTROLE DE OBRA PREMIUM | G1: PLANILHA CONTROLE DE OBRA PREMIUM | H1: PLANILHA CONTROLE DE OBRA PREMIUM
A2: Seu Imovel Sem Arrependimento | J. Edgard Engenharia & Gestao | B2: Seu Imovel Sem Arrependimento | J. Edgard Engenharia & Gestao | C2: Seu Imovel Sem Arrependimento | J. Edgard Engenharia & Gestao | D2: Seu Imovel Sem Arrependimento | J. Edgard Engenharia & Gestao | E2: Seu Imovel Sem Arrependimento | J. Edgard Engenharia & Gestao | F2: Seu Imovel Sem Arrependimento | J. Edgard Engenharia & Gestao | G2: Seu Imovel Sem Arrependimento | J. Edgard Engenharia & Gestao | H2: Seu Imovel Sem Arrependimento | J. Edgard Engenharia & Gestao
A3: Indicador | B3: Valor | D3: Indicador | E3: Valor | G3: Indicador | H3: Valor
A4: Orcamento previsto | B4: =SUM(Orcamento!G4:G18) -> 223000 | D4: Total realizado | E4: =SUM(Orcamento!H4:H18) -> 0 | G4: Saldo previsto | H4: =B4-E4 -> 223000
A5: Pagamentos previstos | B5: =SUM(Pagamentos!F4:F13) -> 39500 | D5: Pagamentos feitos | E5: =SUM(Pagamentos!G4:G13) -> 0 | G5: Aberto a pagar | H5: =B5-E5 -> 39500
A6: Progresso medio | B6: =AVERAGE(Cronograma!G4:G14) -> 0 | D6: Etapas atrasadas | E6: =COUNTIF(Cronograma!H4:H14,"Atrasado") -> 0 | G6: Reserva tecnica | H6: =SUMIF(Orcamento!A4:A18,"Reserva",Orcamento!G4:G18) -> 15000
A8: Instrucoes | B8: Edite as abas Orcamento, Pagamentos e Cronograma.
B9: Use a coluna Realizado para acompanhar gasto real.
B10: Registre fornecedores antes de fechar contrato.
B11: Atualize o Diario de Obra toda semana.
B12: Leve divergencias para o engenheiro responsavel.
A15: Tipo | B15: Previsto | C15: Realizado
A16: Obra | B16: =B4 -> 223000 | C16: =E4 -> 0
A17: Pagamentos | B17: =B5 -> 39500 | C17: =E5 -> 0

Sheet Orcamento
A1: Planilha Controle de Obra - Orcamento | B1: Planilha Controle de Obra - Orcamento | C1: Planilha Controle de Obra - Orcamento | D1: Planilha Controle de Obra - Orcamento | E1: Planilha Controle de Obra - Orcamento | F1: Planilha Controle de Obra - Orcamento | G1: Planilha Controle de Obra - Orcamento | H1: Planilha Controle de Obra - Orcamento | I1: Planilha Controle de Obra - Orcamento | J1: Planilha Controle de Obra - Orcamento
A3: Categoria | B3: Etapa | C3: Item | D3: Unidade | E3: Qtd | F3: Valor unitario | G3: Previsto | H3: Realizado | I3: Diferenca | J3: Status
A4: Projeto | B4: Planejamento | C4: Projeto arquitetonico | D4: un | E4: 1 | F4: 4500 | G4: =E4*F4 -> 4500 | H4: 0 | I4: =H4-G4 -> -4500 | J4: Pendente
A5: Projeto | B5: Planejamento | C5: Projeto estrutural | D5: un | E5: 1 | F5: 3500 | G5: =E5*F5 -> 3500 | H5: 0 | I5: =H5-G5 -> -3500 | J5: Pendente
A6: Terreno | B6: Preparacao | C6: Limpeza do terreno | D6: serv | E6: 1 | F6: 1800 | G6: =E6*F6 -> 1800 | H6: 0 | I6: =H6-G6 -> -1800 | J6: Pendente
A7: Fundacao | B7: Estrutura | C7: Sondagem do solo | D7: un | E7: 1 | F7: 2500 | G7: =E7*F7 -> 2500 | H7: 0 | I7: =H7-G7 -> -2500 | J7: Pendente
A8: Fundacao | B8: Estrutura | C8: Fundacao | D8: serv | E8: 1 | F8: 28000 | G8: =E8*F8 -> 28000 | H8: 0 | I8: =H8-G8 -> -28000 | J8: Pendente
A9: Estrutura | B9: Estrutura | C9: Concreto e ferragem | D9: serv | E9: 1 | F9: 42000 | G9: =E9*F9 -> 42000 | H9: 0 | I9: =H9-G9 -> -42000 | J9: Pendente
A10: Alvenaria | B10: Vedacao | C10: Blocos e argamassa | D10: serv | E10: 1 | F10: 26000 | G10: =E10*F10 -> 26000 | H10: 0 | I10: =H10-G10 -> -26000 | J10: Pendente
A11: Instalacoes | B11: Hidraulica | C11: Material hidraulico | D11: serv | E11: 1 | F11: 12000 | G11: =E11*F11 -> 12000 | H11: 0 | I11: =H11-G11 -> -12000 | J11: Pendente
A12: Instalacoes | B12: Eletrica | C12: Material eletrico | D12: serv | E12: 1 | F12: 14500 | G12: =E12*F12 -> 14500 | H12: 0 | I12: =H12-G12 -> -14500 | J12: Pendente
A13: Cobertura | B13: Telhado | C13: Estrutura e telhas | D13: serv | E13: 1 | F13: 22000 | G13: =E13*F13 -> 22000 | H13: 0 | I13: =H13-G13 -> -22000 | J13: Pendente
A14: Acabamento | B14: Piso | C14: Pisos e revestimentos | D14: m2 | E14: 120 | F14: 140 | G14: =E14*F14 -> 16800 | H14: 0 | I14: =H14-G14 -> -16800 | J14: Pendente
A15: Acabamento | B15: Pintura | C15: Massa e pintura | D15: m2 | E15: 300 | F15: 38 | G15: =E15*F15 -> 11400 | H15: 0 | I15: =H15-G15 -> -11400 | J15: Pendente
... A18: Outros | B18: Geral | C18: Outros custos | D18: un | E18: 1 | F18: 5000 | G18: =E18*F18 -> 5000 | H18: 0 | I18: =H18-G18 -> -5000 | J18: Pendente

Sheet Fornecedores
A1: Cadastro e avaliacao de fornecedores | B1: Cadastro e avaliacao de fornecedores | C1: Cadastro e avaliacao de fornecedores | D1: Cadastro e avaliacao de fornecedores | E1: Cadastro e avaliacao de fornecedores | F1: Cadastro e avaliacao de fornecedores | G1: Cadastro e avaliacao de fornecedores | H1: Cadastro e avaliacao de fornecedores
A3: Fornecedor | B3: Servico | C3: Contato | D3: Orcamento | E3: Prazo | F3: Nota | G3: Risco | H3: Observacoes
B4: Projeto | D4: 0 | G4: Medio
B5: Fundacao | D5: 0 | G5: Alto
B6: Eletrica | D6: 0 | G6: Alto
B7: Hidraulica | D7: 0 | G7: Alto
B8: Acabamento | D8: 0 | G8: Medio
B9: Pintura | D9: 0 | G9: Baixo
B10: Esquadrias | D10: 0 | G10: Medio

Sheet Pagamentos
A1: Controle de pagamentos | B1: Controle de pagamentos | C1: Controle de pagamentos | D1: Controle de pagamentos | E1: Controle de pagamentos | F1: Controle de pagamentos | G1: Controle de pagamentos | H1: Controle de pagamentos
A3: Data | B3: Fornecedor | C3: Categoria | D3: Descricao | E3: Forma | F3: Previsto | G3: Pago | H3: Status
A4: 46178 | B4: Engenheiro/Arquiteto | C4: Projeto | D4: Entrada projeto | E4: Pix | F4: 2500 | G4: 0 | H4: Pendente
A5: 46193 | B5: Topografia | C5: Terreno | D5: Levantamento inicial | E5: Pix | F5: 1500 | G5: 0 | H5: Pendente
A6: 46208 | B6: Sondagem | C6: Fundacao | D6: Sondagem do solo | E6: Pix | F6: 2500 | G6: 0 | H6: Pendente
A7: 46223 | B7: Empreiteiro | C7: Fundacao | D7: 1a medicao | E7: Transferencia | F7: 15000 | G7: 0 | H7: Pendente
A8: 46249 | B8: Material | C8: Estrutura | D8: Concreto e ferragem | E8: Boleto | F8: 18000 | G8: 0 | H8: Pendente
F9: 0 | G9: 0 | H9: Pendente
F10: 0 | G10: 0 | H10: Pendente
F11: 0 | G11: 0 | H11: Pendente
F12: 0 | G12: 0 | H12: Pendente
F13: 0 | G13: 0 | H13: Pendente

Sheet Cronograma
A1: Cronograma fisico da obra | B1: Cronograma fisico da obra | C1: Cronograma fisico da obra | D1: Cronograma fisico da obra | E1: Cronograma fisico da obra | F1: Cronograma fisico da obra | G1: Cronograma fisico da obra | H1: Cronograma fisico da obra
A3: Etapa | B3: Responsavel | C3: Inicio previsto | D3: Fim previsto | E3: Inicio real | F3: Fim real | G3: % concluido | H3: Status
A4: Projetos | C4: 46174 | D4: 46203 | G4: 0 | H4: Pendente
A5: Aprovacoes | C5: 46204 | D5: 46223 | G5: 0 | H5: Pendente
A6: Terreno | C6: 46224 | D6: 46234 | G6: 0 | H6: Pendente
A7: Fundacao | C7: 46235 | D7: 46259 | G7: 0 | H7: Pendente
A8: Estrutura | C8: 46260 | D8: 46300 | G8: 0 | H8: Pendente
A9: Alvenaria | C9: 46301 | D9: 46341 | G9: 0 | H9: Pendente
A10: Instalacoes | C10: 46342 | D10: 46376 | G10: 0 | H10: Pendente
A11: Cobertura | C11: 46392 | D11: 46412 | G11: 0 | H11: Pendente
A12: Acabamentos | C12: 46413 | D12: 46466 | G12: 0 | H12: Pendente
A13: Vistoria final | C13: 46467 | D13: 46477 | G13: 0 | H13: Pendente
A14: Entrega | C14: 46478 | D14: 46482 | G14: 0 | H14: Pendente

Sheet Diario de Obra
A1: Diario de obra | B1: Diario de obra | C1: Diario de obra | D1: Diario de obra | E1: Diario de obra | F1: Diario de obra | G1: Diario de obra
A3: Data | B3: Clima | C3: Equipe | D3: Atividades executadas | E3: Ocorrencias | F3: Fotos/links | G3: Proxima acao
